fs_miniofs/__init__.py
fs_miniofs/_miniofs.py
fs_miniofs/_version.py
fs_miniofs/opener.py
fs_miniofs-1.1.2.dist-info/LICENSE
fs_miniofs-1.1.2.dist-info/METADATA
fs_miniofs-1.1.2.dist-info/WHEEL
fs_miniofs-1.1.2.dist-info/entry_points.txt
fs_miniofs-1.1.2.dist-info/top_level.txt
fs_miniofs-1.1.2.dist-info/RECORD
